MargotRobbie/__init__.py
MargotRobbie-1.0.0.dist-info/LICENSE
MargotRobbie-1.0.0.dist-info/METADATA
MargotRobbie-1.0.0.dist-info/WHEEL
MargotRobbie-1.0.0.dist-info/top_level.txt
MargotRobbie-1.0.0.dist-info/RECORD
